dictlistdict.py
nesteddict.py
nesteddict-0.1.3.dist-info/LICENSE
nesteddict-0.1.3.dist-info/METADATA
nesteddict-0.1.3.dist-info/WHEEL
nesteddict-0.1.3.dist-info/entry_points.txt
nesteddict-0.1.3.dist-info/top_level.txt
nesteddict-0.1.3.dist-info/RECORD
