Metadata-Version: 2.1
Name: nesteddict
Version: 0.1.3
Summary: A sub-class of dict that allows nested key access e.g. a['a.b.c']
Home-page: https://github.com/jdrumgoole/nesteddict
Author: Joe Drumgoole
Author-email: joe@joedrumgoole.com
License: MIT
Platform: UNKNOWN
Classifier: License :: OSI Approved :: MIT License
Classifier: Programming Language :: Python
Classifier: Programming Language :: Python :: 3
Classifier: Programming Language :: Python :: 3.6
Classifier: Programming Language :: Python :: Implementation :: CPython
Classifier: Programming Language :: Python :: Implementation :: PyPy
Requires-Python: >=3.5.0
